kubetemplatespawner/__init__.py
kubetemplatespawner/_kubernetes.py
kubetemplatespawner/_version.py
kubetemplatespawner/spawner.py
kubetemplatespawner-0.1.0.dist-info/licenses/LICENSE
kubetemplatespawner-0.1.0.dist-info/METADATA
kubetemplatespawner-0.1.0.dist-info/WHEEL
kubetemplatespawner-0.1.0.dist-info/entry_points.txt
kubetemplatespawner-0.1.0.dist-info/top_level.txt
kubetemplatespawner-0.1.0.dist-info/RECORD
