Metadata-Version: 2.4
Name: kubetemplatespawner
Version: 0.1.0
Summary: JupyterHub Kubernetes template spawner
Author: Simon Li
License-Expression: BSD-3-Clause
Project-URL: Repository, https://github.com/manics/kubetemplatespawner.git
Project-URL: Issues, https://github.com/manics/kubetemplatespawner/issues
Keywords: jupyter,jupyterhub
Classifier: Development Status :: 2 - Pre-Alpha
Classifier: Framework :: Jupyter
Classifier: Intended Audience :: Developers
Classifier: Intended Audience :: System Administrators
Classifier: Programming Language :: Python
Requires-Python: >=3.12
License-File: LICENSE
Requires-Dist: pyyaml>=6.0.2
Requires-Dist: jupyterhub>=5.2.0
Requires-Dist: kubernetes_asyncio>=31.1.0
Requires-Dist: traitlets>=5.14.3
Requires-Dist: jupyterhub-kubespawner>=7.0.0
Provides-Extra: dev
Requires-Dist: build>=1.2.2; extra == "dev"
Requires-Dist: pre_commit>=4.1.0; extra == "dev"
Requires-Dist: pytest>=8.3.4; extra == "dev"
Requires-Dist: pytest-asyncio>=0.25.3; extra == "dev"
Requires-Dist: pytest-mock>=3.14.0; extra == "dev"
Dynamic: license-file
